{
  "adult": true,
  "backdrop_path": null,
  "belongs_to_collection": null,
  "budget": 0,
  "genres": [
    {
      "id": 79,
      "name": "Beautiful Breasts"
    },
    {
      "id": 0,
      "name": "Pretty Girl"
    },
    {
      "id": 60,
      "name": "Ordinary Person"
    },
    {
      "id": 40,
      "name": "Creampie"
    },
    {
      "id": 87,
      "name": "Orgy"
    }
  ],
  "homepage": "https://missav.ai",
  "id": "saba-091",
  "imdb_id": "saba-091",
  "origin_country": "JP",
  "original_language": "jp",
  "original_title": "SABA-091 Flowering Woman Venus #14",
  "overview": "Aoi of the innocent school, with innocent eyes like a curly girl. I thought that her body was also a loli loli, but when she took off her clothes, she unexpectedly spilled out her beautiful G-cup breasts that you can't even imagine! The size of this gap makes the excitement level MAX and the tension is at its peak! This is exactly what women are in full bloom!",
  "popularity": 0,
  "poster_path": "https://fourhoi.com/saba-091/cover.jpg",
  "production_companies": [
    {
      "id": "S級素人",
      "logo_path": "https://placehold.co/200",
      "name": "S%E7%B4%9A%E7%B4%A0%E4%BA%BA",
      "origin_country": "JP"
    }
  ],
  "production_countries": [
    {
      "iso_3166_1": "JP",
      "name": "Japan"
    }
  ],
  "release_date": "2014-05-23",
  "revenue": 0,
  "runtime": 114,
  "spoken_languages": [
    {
      "iso_639_1": "ja",
      "name": "Japanese"
    }
  ],
  "status": "Released",
  "tagline": "Adult",
  "title": "SABA 091",
  "video": null,
  "vote_average": 0,
  "vote_count": 0,
  "sources": [],
  "keywords": {
    "keywords": [
      {
        "id": null,
        "name": null
      }
    ]
  },
  "credits": {
    "cast": [],
    "crew": [
      {
        "adult": true,
        "gender": null,
        "id": "S%E7%B4%9A%E7%B4%A0%E4%BA%BA",
        "known_for_department": "Directing",
        "name": "S級素人",
        "popularity": null,
        "profile_path": "https://placehold.co/200",
        "credit_id": null,
        "department": "Directing",
        "job": "Director"
      }
    ]
  }
}