{
  "adult": true,
  "backdrop_path": null,
  "belongs_to_collection": null,
  "budget": 0,
  "genres": [
    {
      "id": 46,
      "name": "Shame"
    },
    {
      "id": 18,
      "name": "Planning"
    },
    {
      "id": 97,
      "name": "Individual"
    },
    {
      "id": 20,
      "name": "Vibrating Egg"
    },
    {
      "id": 78,
      "name": "Hd"
    }
  ],
  "homepage": "https://missav.ai",
  "id": "svdvd-410",
  "imdb_id": "svdvd-410",
  "origin_country": "JP",
  "original_language": "jp",
  "original_title": "SVDVD-410 I Inserted A Big Bang Rotor Into Kofuyu Suzuki's Pussy And Made Her Work Part-time At A Bakery Seriously! - Suzuki Koharu",
  "overview": "apology. It's too late, but in the series of Big Bang Rotor works, our company was doing so-called \"fucking\". I deeply regret it. By the way, do you know? A legendary project from a dozen-odd years ago in SOD, ``The female crew of a ``major hamburger restaurant'' was made to work with a flying rotor. This time, I tried to imitate that project with \"No Yarase\".",
  "popularity": 0,
  "poster_path": "https://fourhoi.com/svdvd-410/cover.jpg",
  "production_companies": [
    {
      "id": "Sadistic Village",
      "logo_path": "https://placehold.co/200",
      "name": "Sadistic%20Village",
      "origin_country": "JP"
    }
  ],
  "production_countries": [
    {
      "iso_3166_1": "JP",
      "name": "Japan"
    }
  ],
  "release_date": "2014-05-22",
  "revenue": 0,
  "runtime": 166,
  "spoken_languages": [
    {
      "iso_639_1": "ja",
      "name": "Japanese"
    }
  ],
  "status": "Released",
  "tagline": "Adult",
  "title": "SVDVD 410",
  "video": null,
  "vote_average": 0,
  "vote_count": 0,
  "sources": [],
  "keywords": {
    "keywords": [
      {
        "id": null,
        "name": null
      }
    ]
  },
  "credits": {
    "cast": [
      {
        "adult": true,
        "gender": 1,
        "id": "Suzuki Koharu",
        "known_for_department": "Acting",
        "name": "Suzuki Koharu",
        "popularity": null,
        "profile_path": "https://placehold.co/200",
        "cast_id": null,
        "character": null,
        "credit_id": null,
        "order": null
      }
    ],
    "crew": [
      {
        "adult": true,
        "gender": null,
        "id": "Sadistic%20Village",
        "known_for_department": "Directing",
        "name": "Sadistic Village",
        "popularity": null,
        "profile_path": "https://placehold.co/200",
        "credit_id": null,
        "department": "Directing",
        "job": "Director"
      }
    ]
  }
}