{
  "adult": true,
  "backdrop_path": null,
  "belongs_to_collection": null,
  "budget": 0,
  "genres": [
    {
      "id": 8,
      "name": "Pretty Girl"
    },
    {
      "id": 25,
      "name": "Swimsuit"
    },
    {
      "id": 95,
      "name": "Sneak Shots"
    },
    {
      "id": 40,
      "name": "Individual"
    },
    {
      "id": 28,
      "name": "Group Bukkake"
    },
    {
      "id": 57,
      "name": "Hd"
    }
  ],
  "homepage": "https://missav.ai",
  "id": "okk-018",
  "imdb_id": "okk-018",
  "origin_country": "JP",
  "original_language": "jp",
  "original_title": "OKK-018 Wet and shiny, perfect fit God swimsuit Aya Mamiya Lori Enjoy the cute girls' swimsuits! AV that starts with changing clothes voyeur and enjoys fetish close-ups such as shaved breasts, Hami hair, Joriwaki, lotion soap play, swimsuit bukkake, etc. from small breasts to big breasts",
  "overview": "From loli beautiful girl to married woman mature woman giving a swimsuit to a cute woman and starting from changing clothes voyeur, from do-up close-up shooting that slowly licks big breasts, shaved hair, Hami hair, armpit, lotion play and masturbation, excitement blowjob and raw vaginal cum shot H and swimsuit bukkake And many other fetish videos of my father who loves swimsuits! Full-length fully-clothed AV that never takes off the swimsuit.",
  "popularity": 0,
  "poster_path": "https://fourhoi.com/okk-018/cover.jpg",
  "production_companies": [
    {
      "id": "親父の個撮",
      "logo_path": "https://placehold.co/200",
      "name": "%E8%A6%AA%E7%88%B6%E3%81%AE%E5%80%8B%E6%92%AE",
      "origin_country": "JP"
    }
  ],
  "production_countries": [
    {
      "iso_3166_1": "JP",
      "name": "Japan"
    }
  ],
  "release_date": "2020-09-10",
  "revenue": 0,
  "runtime": 92,
  "spoken_languages": [
    {
      "iso_639_1": "ja",
      "name": "Japanese"
    }
  ],
  "status": "Released",
  "tagline": "Adult",
  "title": "OKK 018",
  "video": null,
  "vote_average": 0,
  "vote_count": 0,
  "sources": [],
  "keywords": {
    "keywords": [
      {
        "id": null,
        "name": null
      }
    ]
  },
  "credits": {
    "cast": [
      {
        "adult": true,
        "gender": 1,
        "id": "Aya Mamiya",
        "known_for_department": "Acting",
        "name": "Aya Mamiya",
        "popularity": null,
        "profile_path": "https://placehold.co/200",
        "cast_id": null,
        "character": null,
        "credit_id": null,
        "order": null
      }
    ],
    "crew": [
      {
        "adult": true,
        "gender": null,
        "id": "%E8%A6%AA%E7%88%B6%E3%81%AE%E5%80%8B%E6%92%AE",
        "known_for_department": "Directing",
        "name": "親父の個撮",
        "popularity": null,
        "profile_path": "https://placehold.co/200",
        "credit_id": null,
        "department": "Directing",
        "job": "Director"
      }
    ]
  }
}