{
  "adult": true,
  "backdrop_path": null,
  "belongs_to_collection": null,
  "budget": 0,
  "genres": [
    {
      "id": 63,
      "name": "Collection"
    },
    {
      "id": 45,
      "name": "4 Hours Or More"
    },
    {
      "id": 62,
      "name": "Exclusive"
    }
  ],
  "homepage": "https://missav.ai",
  "id": "scf-057",
  "imdb_id": "scf-057",
  "origin_country": "JP",
  "original_language": "jp",
  "original_title": "SCF-057 No Panties High School 12 Hours BOX - Erika (Moka)",
  "overview": "School Revolution of the sexy and cute devilish gal! The naughty no-panties school life of modern schoolgirls. Don't take off my uniform... A cool and hot no-panties school. It's a special lesson, the gal in uniform bounces her ass and cums like crazy!",
  "popularity": 0,
  "poster_path": "https://fourhoi.com/scf-057/cover.jpg",
  "production_companies": [
    {
      "id": "MARX",
      "logo_path": "https://placehold.co/200",
      "name": "MARX",
      "origin_country": "JP"
    }
  ],
  "production_countries": [
    {
      "iso_3166_1": "JP",
      "name": "Japan"
    }
  ],
  "release_date": "2014-05-23",
  "revenue": 0,
  "runtime": 718,
  "spoken_languages": [
    {
      "iso_639_1": "ja",
      "name": "Japanese"
    }
  ],
  "status": "Released",
  "tagline": "Adult",
  "title": "SCF 057",
  "video": null,
  "vote_average": 0,
  "vote_count": 0,
  "sources": [],
  "keywords": {
    "keywords": [
      {
        "id": null,
        "name": null
      }
    ]
  },
  "credits": {
    "cast": [
      {
        "adult": true,
        "gender": 1,
        "id": "Erika (Moka)",
        "known_for_department": "Acting",
        "name": "Erika (Moka)",
        "popularity": null,
        "profile_path": "https://placehold.co/200",
        "cast_id": null,
        "character": null,
        "credit_id": null,
        "order": null
      },
      {
        "adult": true,
        "gender": 1,
        "id": "Rui Saotome",
        "known_for_department": "Acting",
        "name": "Rui Saotome",
        "popularity": null,
        "profile_path": "https://placehold.co/200",
        "cast_id": null,
        "character": null,
        "credit_id": null,
        "order": null
      },
      {
        "adult": true,
        "gender": 1,
        "id": "Fuka Nanasaki (Kaede Nanasaki)",
        "known_for_department": "Acting",
        "name": "Fuka Nanasaki (Kaede Nanasaki)",
        "popularity": null,
        "profile_path": "https://placehold.co/200",
        "cast_id": null,
        "character": null,
        "credit_id": null,
        "order": null
      },
      {
        "adult": true,
        "gender": 1,
        "id": "Risa Tsukino",
        "known_for_department": "Acting",
        "name": "Risa Tsukino",
        "popularity": null,
        "profile_path": "https://placehold.co/200",
        "cast_id": null,
        "character": null,
        "credit_id": null,
        "order": null
      },
      {
        "adult": true,
        "gender": 1,
        "id": "Shinmi Naruse (Kokomi)",
        "known_for_department": "Acting",
        "name": "Shinmi Naruse (Kokomi)",
        "popularity": null,
        "profile_path": "https://placehold.co/200",
        "cast_id": null,
        "character": null,
        "credit_id": null,
        "order": null
      },
      {
        "adult": true,
        "gender": 1,
        "id": "Otowa Leon",
        "known_for_department": "Acting",
        "name": "Otowa Leon",
        "popularity": null,
        "profile_path": "https://placehold.co/200",
        "cast_id": null,
        "character": null,
        "credit_id": null,
        "order": null
      },
      {
        "adult": true,
        "gender": 1,
        "id": "Mahiro Aine",
        "known_for_department": "Acting",
        "name": "Mahiro Aine",
        "popularity": null,
        "profile_path": "https://placehold.co/200",
        "cast_id": null,
        "character": null,
        "credit_id": null,
        "order": null
      },
      {
        "adult": true,
        "gender": 1,
        "id": "Azumi",
        "known_for_department": "Acting",
        "name": "Azumi",
        "popularity": null,
        "profile_path": "https://placehold.co/200",
        "cast_id": null,
        "character": null,
        "credit_id": null,
        "order": null
      },
      {
        "adult": true,
        "gender": 1,
        "id": "Rumika",
        "known_for_department": "Acting",
        "name": "Rumika",
        "popularity": null,
        "profile_path": "https://placehold.co/200",
        "cast_id": null,
        "character": null,
        "credit_id": null,
        "order": null
      },
      {
        "adult": true,
        "gender": 1,
        "id": "Aoshino (Megumi Shino)",
        "known_for_department": "Acting",
        "name": "Aoshino (Megumi Shino)",
        "popularity": null,
        "profile_path": "https://placehold.co/200",
        "cast_id": null,
        "character": null,
        "credit_id": null,
        "order": null
      },
      {
        "adult": true,
        "gender": 1,
        "id": "Mana Izumi",
        "known_for_department": "Acting",
        "name": "Mana Izumi",
        "popularity": null,
        "profile_path": "https://placehold.co/200",
        "cast_id": null,
        "character": null,
        "credit_id": null,
        "order": null
      },
      {
        "adult": true,
        "gender": 1,
        "id": "Yu Asakura",
        "known_for_department": "Acting",
        "name": "Yu Asakura",
        "popularity": null,
        "profile_path": "https://placehold.co/200",
        "cast_id": null,
        "character": null,
        "credit_id": null,
        "order": null
      },
      {
        "adult": true,
        "gender": 1,
        "id": "Shiina Tsubame",
        "known_for_department": "Acting",
        "name": "Shiina Tsubame",
        "popularity": null,
        "profile_path": "https://placehold.co/200",
        "cast_id": null,
        "character": null,
        "credit_id": null,
        "order": null
      },
      {
        "adult": true,
        "gender": 1,
        "id": "Miho Imamura",
        "known_for_department": "Acting",
        "name": "Miho Imamura",
        "popularity": null,
        "profile_path": "https://placehold.co/200",
        "cast_id": null,
        "character": null,
        "credit_id": null,
        "order": null
      },
      {
        "adult": true,
        "gender": 1,
        "id": "Nishina Hyakuka",
        "known_for_department": "Acting",
        "name": "Nishina Hyakuka",
        "popularity": null,
        "profile_path": "https://placehold.co/200",
        "cast_id": null,
        "character": null,
        "credit_id": null,
        "order": null
      },
      {
        "adult": true,
        "gender": 1,
        "id": "Rin Aikawa",
        "known_for_department": "Acting",
        "name": "Rin Aikawa",
        "popularity": null,
        "profile_path": "https://placehold.co/200",
        "cast_id": null,
        "character": null,
        "credit_id": null,
        "order": null
      },
      {
        "adult": true,
        "gender": 1,
        "id": "Kitagawa Hitomi",
        "known_for_department": "Acting",
        "name": "Kitagawa Hitomi",
        "popularity": null,
        "profile_path": "https://placehold.co/200",
        "cast_id": null,
        "character": null,
        "credit_id": null,
        "order": null
      },
      {
        "adult": true,
        "gender": 1,
        "id": "Haruki Sato",
        "known_for_department": "Acting",
        "name": "Haruki Sato",
        "popularity": null,
        "profile_path": "https://placehold.co/200",
        "cast_id": null,
        "character": null,
        "credit_id": null,
        "order": null
      }
    ],
    "crew": [
      {
        "adult": true,
        "gender": null,
        "id": "MARX",
        "known_for_department": "Directing",
        "name": "MARX",
        "popularity": null,
        "profile_path": "https://placehold.co/200",
        "credit_id": null,
        "department": "Directing",
        "job": "Director"
      }
    ]
  }
}