{
  "adult": true,
  "backdrop_path": null,
  "belongs_to_collection": null,
  "budget": 0,
  "genres": [
    {
      "id": 63,
      "name": "Swimsuit"
    },
    {
      "id": 41,
      "name": "Underwear"
    },
    {
      "id": 88,
      "name": "Ordinary Person"
    },
    {
      "id": 23,
      "name": "Erotic Photo"
    },
    {
      "id": 99,
      "name": "Toy"
    },
    {
      "id": 50,
      "name": "Hd"
    }
  ],
  "homepage": "https://missav.ai",
  "id": "ram-129",
  "imdb_id": "ram-129",
  "origin_country": "JP",
  "original_language": "jp",
  "original_title": "RAM-129 NO Mosaic! ! Super close-up! ! Kimono Collection",
  "overview": "Bite, cameltoe, see-through man, Hami hair, stain fetish must-see! clearly! Plump! erection! Transparent! The shape of the dick is completely understood! The ultimate no mosaic clothed pussy video collection that is more erotic than raw, photographed from a super close distance between the crotch of a girl who appeals fiercely through clothes! A total of 13 outfits that you can't usually stare at, and we'll deliver them to the very limit!",
  "popularity": 0,
  "poster_path": "https://fourhoi.com/ram-129/cover.jpg",
  "production_companies": [
    {
      "id": "サルトル映像出版",
      "logo_path": "https://placehold.co/200",
      "name": "%E3%82%B5%E3%83%AB%E3%83%88%E3%83%AB%E6%98%A0%E5%83%8F%E5%87%BA%E7%89%88",
      "origin_country": "JP"
    }
  ],
  "production_countries": [
    {
      "iso_3166_1": "JP",
      "name": "Japan"
    }
  ],
  "release_date": "2014-06-04",
  "revenue": 0,
  "runtime": 104,
  "spoken_languages": [
    {
      "iso_639_1": "ja",
      "name": "Japanese"
    }
  ],
  "status": "Released",
  "tagline": "Adult",
  "title": "RAM 129",
  "video": null,
  "vote_average": 0,
  "vote_count": 0,
  "sources": [],
  "keywords": {
    "keywords": [
      {
        "id": null,
        "name": null
      }
    ]
  },
  "credits": {
    "cast": [],
    "crew": [
      {
        "adult": true,
        "gender": null,
        "id": "%E3%82%B5%E3%83%AB%E3%83%88%E3%83%AB%E6%98%A0%E5%83%8F%E5%87%BA%E7%89%88",
        "known_for_department": "Directing",
        "name": "サルトル映像出版",
        "popularity": null,
        "profile_path": "https://placehold.co/200",
        "credit_id": null,
        "department": "Directing",
        "job": "Director"
      }
    ]
  }
}