{"las-026":"en/la/s-/02/en-las-026.json","luke-009":"en/lu/ke/-0/en-luke-009.json","lady-348":"en/la/dy/-3/en-lady-348.json","lady-349":"en/la/dy/-3/en-lady-349.json","lady-350":"en/la/dy/-3/en-lady-350.json","loli-027":"en/lo/li/-0/en-loli-027.json","loli-028":"en/lo/li/-0/en-loli-028.json","lulu-111-uncensored-leak":"en/lu/lu/-1/en-lulu-111-uncensored-leak.json","luxu-1876":"en/lu/xu/-1/en-luxu-1876.json","lulu-123-uncensored-leak":"en/lu/lu/-1/en-lulu-123-uncensored-leak.json","lulu-122-uncensored-leak":"en/lu/lu/-1/en-lulu-122-uncensored-leak.json","luke-030-uncensored-leak":"en/lu/ke/-0/en-luke-030-uncensored-leak.json"}