{
  "adult": true,
  "backdrop_path": null,
  "belongs_to_collection": null,
  "budget": 0,
  "genres": [
    {
      "id": 32,
      "name": "Shame"
    },
    {
      "id": 28,
      "name": "Ol"
    },
    {
      "id": 71,
      "name": "Big Breasts"
    },
    {
      "id": 54,
      "name": "Ordinary Person"
    },
    {
      "id": 8,
      "name": "Urinate"
    },
    {
      "id": 66,
      "name": "4 Hours Or More"
    },
    {
      "id": 56,
      "name": "Hd"
    }
  ],
  "homepage": "https://missav.ai",
  "id": "sdjs-073",
  "imdb_id": "sdjs-073",
  "origin_country": "JP",
  "original_language": "jp",
  "original_title": "SDJS-073 SOD Female Employees Limited to New Employees Naked Health Examination Full of Big Breasts Nine people with well-grown, edible bodies were naked and seriously examined (Heart)",
  "overview": "[Big pie new employees gathered! ] It is the role of the company to protect the health of employees! We asked the first-year students who had just joined the company to be naked in the company and examined every corner of their bodies! The target is 9 big breasts with remarkable physical development! Big ass with plenty of boobs! Still, everyone is still small and immature (# ^. ^ #) Only Ma ● Ko is examined by throwing in a meat stick!",
  "popularity": 0,
  "poster_path": "https://fourhoi.com/sdjs-073/cover.jpg",
  "production_companies": [
    {
      "id": "SOD",
      "logo_path": "https://placehold.co/200",
      "name": "SOD",
      "origin_country": "JP"
    }
  ],
  "production_countries": [
    {
      "iso_3166_1": "JP",
      "name": "Japan"
    }
  ],
  "release_date": "2020-09-15",
  "revenue": 0,
  "runtime": 242,
  "spoken_languages": [
    {
      "iso_639_1": "ja",
      "name": "Japanese"
    }
  ],
  "status": "Released",
  "tagline": "Adult",
  "title": "SDJS 073",
  "video": null,
  "vote_average": 0,
  "vote_count": 0,
  "sources": [],
  "keywords": {
    "keywords": [
      {
        "id": null,
        "name": null
      }
    ]
  },
  "credits": {
    "cast": [],
    "crew": [
      {
        "adult": true,
        "gender": null,
        "id": "SOD",
        "known_for_department": "Directing",
        "name": "SOD",
        "popularity": null,
        "profile_path": "https://placehold.co/200",
        "credit_id": null,
        "department": "Directing",
        "job": "Director"
      }
    ]
  }
}