{
  "adult": true,
  "backdrop_path": null,
  "belongs_to_collection": null,
  "budget": 0,
  "genres": [
    {
      "id": 10,
      "name": "Wife"
    },
    {
      "id": 46,
      "name": "Adultery"
    },
    {
      "id": 56,
      "name": "Sneak Shots"
    },
    {
      "id": 65,
      "name": "Individual"
    },
    {
      "id": 59,
      "name": "Plot"
    }
  ],
  "homepage": "https://missav.ai",
  "id": "acy-001",
  "imdb_id": "acy-001",
  "origin_country": "JP",
  "original_language": "jp",
  "original_title": "ACY-001 Married Woman Peeping Rina Yoshiguchi",
  "overview": "Married woman 'Rina''s apartment is being looked into by a university student. Rina who noticed it intentionally tempts college students. A story in which a college student who is addicted to Rina and her true nature intersect.",
  "popularity": 0,
  "poster_path": "https://fourhoi.com/acy-001/cover.jpg",
  "production_companies": [
    {
      "id": "Glory Quest",
      "logo_path": "https://placehold.co/200",
      "name": "Glory%20Quest",
      "origin_country": "JP"
    }
  ],
  "production_countries": [
    {
      "iso_3166_1": "JP",
      "name": "Japan"
    }
  ],
  "release_date": "2014-05-15",
  "revenue": 0,
  "runtime": 88,
  "spoken_languages": [
    {
      "iso_639_1": "ja",
      "name": "Japanese"
    }
  ],
  "status": "Released",
  "tagline": "Adult",
  "title": "ACY 001",
  "video": null,
  "vote_average": 0,
  "vote_count": 0,
  "sources": [],
  "keywords": {
    "keywords": [
      {
        "id": null,
        "name": null
      }
    ]
  },
  "credits": {
    "cast": [
      {
        "adult": true,
        "gender": 1,
        "id": "Rina Yoshiguchi",
        "known_for_department": "Acting",
        "name": "Rina Yoshiguchi",
        "popularity": null,
        "profile_path": "https://placehold.co/200",
        "cast_id": null,
        "character": null,
        "credit_id": null,
        "order": null
      }
    ],
    "crew": [
      {
        "adult": true,
        "gender": null,
        "id": "Glory%20Quest",
        "known_for_department": "Directing",
        "name": "Glory Quest",
        "popularity": null,
        "profile_path": "https://placehold.co/200",
        "credit_id": null,
        "department": "Directing",
        "job": "Director"
      }
    ]
  }
}