{
  "adult": true,
  "backdrop_path": null,
  "belongs_to_collection": null,
  "budget": 0,
  "genres": [
    {
      "id": 85,
      "name": "Uncensored leak"
    },
    {
      "id": 48,
      "name": "Pretty Girl"
    },
    {
      "id": 67,
      "name": "Butt Fetish"
    },
    {
      "id": 51,
      "name": "Individual"
    },
    {
      "id": 73,
      "name": "Creampie"
    },
    {
      "id": 57,
      "name": "Selfie"
    },
    {
      "id": 56,
      "name": "Hd"
    },
    {
      "id": 55,
      "name": "Exclusive"
    },
    {
      "id": 0,
      "name": "Delusion"
    }
  ],
  "homepage": "https://missav.ai",
  "id": "pkpr-021-uncensored-leak",
  "imdb_id": "pkpr-021-uncensored-leak",
  "origin_country": "JP",
  "original_language": "jp",
  "original_title": "PKPR-021 Sweetheart Love Document A one-day flirty date with Natsushiro Maya, a new girl with a beautiful butt - Natsushira Maya",
  "overview": "Maya Natsushiro has a slightly silly and honest personality. At the same time, she attracts men with her top-notch beautiful butt. He has an honest personality that makes you think that he really became a lover through this lover's contract. It would be sad to see her as someone who is serious about a man, whether it's on a date or in bed, and that they would no longer be lovers in one day. That's what I honestly thought.",
  "popularity": 0,
  "poster_path": "https://fourhoi.com/pkpr-021-uncensored-leak/cover.jpg",
  "production_companies": [
    {
      "id": "パコパコ団とゆかいな仲間たち/妄想族",
      "logo_path": "https://placehold.co/200",
      "name": "パコパコ団とゆかいな仲間たち/妄想族",
      "origin_country": "JP"
    }
  ],
  "production_countries": [
    {
      "iso_3166_1": "JP",
      "name": "Japan"
    }
  ],
  "release_date": "2023-12-02",
  "revenue": 0,
  "runtime": 139,
  "spoken_languages": [
    {
      "iso_639_1": "ja",
      "name": "Japanese"
    }
  ],
  "status": "Released",
  "tagline": "Adult",
  "title": "PKPR 021 Uncensored Leak",
  "video": null,
  "vote_average": 0,
  "vote_count": 0,
  "sources": [],
  "keywords": {
    "keywords": [
      {
        "id": null,
        "name": null
      }
    ]
  },
  "credits": {
    "cast": [
      {
        "adult": true,
        "gender": 1,
        "id": "Natsushira Maya",
        "known_for_department": "Acting",
        "name": "Natsushira Maya",
        "popularity": null,
        "profile_path": "https://placehold.co/200",
        "cast_id": null,
        "character": null,
        "credit_id": null,
        "order": null
      }
    ],
    "crew": [
      {
        "adult": true,
        "gender": null,
        "id": "%E5%A6%84%E6%83%B3%E6%97%8F",
        "known_for_department": "Directing",
        "name": "パコパコ団とゆかいな仲間たち/妄想族",
        "popularity": null,
        "profile_path": "https://placehold.co/200",
        "credit_id": null,
        "department": "Directing",
        "job": "Director"
      }
    ]
  }
}