{
  "id": "migd-588",
  "title": "MIGD-588 Dream Woman Vol.96 Shoko Akiyama",
  "overview": "Finally, Shoko Akiyama lifts the ban on mass bukkake! Moreover, it first appeared in \"Dream Woman\"! !! A large amount of 121 stinking and thick raw semen is fired at an S-class beauty sister who is too beautiful! !! \"I love dull sperm the most\" Dirty full-throttle mode that answers with a smile! Sucking regardless of the surrounding cock! Bukkake on a fascinating beauty! Only MOODYZ can see Shoko Akiyama getting dirty!",
  "poster_path": "https://fourhoi.com/migd-588/cover.jpg",
  "release_date": "2014-05-11\n                            2 weeks ago\n                        \n                            2 weeks ago\n                        \n                            1 year ago\n                        \n                            1 year ago\n                        \n                            1 year ago\n                        \n                            1 year ago\n                        \n                            1 year ago\n                        \n                            1 year ago\n                        \n                            1 year ago\n                        \n                            1 year ago\n                        ",
  "runtime": 108,
  "sources": []
}