{
  "id": "pssd-336",
  "title": "PSSD-336 Best of Rina Fukada - Rina Fukada (Rina Fukada)",
  "overview": "In \"Female anthology #098\", she first played the role of a female teacher. A teacher with high pride provokes with a dirty word from above. Next is the role of stalker. Don't miss the fear experienced by a man who knows he's a scary woman and accidentally fucks him! The last is her role. Rina-chan's first Nyan Nyan challenge. In \"Forbidden Family Love\", hot kisses from spitting, cunnilingus, fingering and rich lesbian play! In \"DOKI Lesbian 58\", please enjoy Rina-chan's \"raw\" sex!",
  "poster_path": "https://fourhoi.com/pssd-336/cover.jpg",
  "release_date": "2014-05-27",
  "runtime": 247,
  "sources": []
}