{
  "id": "shim-004",
  "title": "SHIM-004 Wandering Gonzo Shohei Shima Goes Nationwide Married Woman Affair Caravan Vol.04",
  "overview": "Chasing a shy married woman and a frustrated housewife, I will fuck you in the north, south, east, and west. So, thank you. This time, we will deliver to you a video that made you say hee hee after defeating three exceptional women. Well then, let's find the next woman and fuck her! !",
  "poster_path": "https://fourhoi.com/shim-004/cover.jpg",
  "release_date": "2014-05-28",
  "runtime": 122,
  "sources": []
}