{
  "id": "yst-002",
  "title": "YST-002 Raw Adultery 02 - Rei Aimi",
  "overview": "Rei, a hairless wife with a smooth pussy, loves to tease men with her clear skin and firm G-cup breasts. With a dreamy look on her face, she devours the man's cock lovingly, servicing him deeply with her mouth and throat, tasting his hot semen, and seducing him further with her moist eyes. Rina, a young wife, wraps her beautiful legs around the man's waist and stares longingly at his penis. She happily takes the erect cock in front of her in her mouth, sucks out the pre-cum with her lewd tongue, inviting him to ejaculate, and then fills her mouth with semen. After that, she squirts in agony as her wet pussy is fingered, and then has cunnilingus on her squirting pussy, bringing her to orgasm.",
  "poster_path": "https://fourhoi.com/yst-002/cover.jpg",
  "release_date": "2014-05-15",
  "runtime": 120,
  "sources": []
}