{
  "adult": true,
  "backdrop_path": null,
  "belongs_to_collection": null,
  "budget": 0,
  "genres": [
    {
      "id": 76,
      "name": "Uncensored leak"
    },
    {
      "id": 16,
      "name": "Campus Story"
    },
    {
      "id": 96,
      "name": "In Love"
    },
    {
      "id": 53,
      "name": "Female Teacher"
    },
    {
      "id": 84,
      "name": "Virgin"
    },
    {
      "id": 43,
      "name": "Individual"
    },
    {
      "id": 18,
      "name": "Orgy"
    },
    {
      "id": 23,
      "name": "Slim Pixelated"
    },
    {
      "id": 1,
      "name": "Hd"
    },
    {
      "id": 22,
      "name": "Exclusive"
    }
  ],
  "homepage": "https://missav.ai",
  "id": "miaa-097-uncensored-leak",
  "imdb_id": "miaa-097-uncensored-leak",
  "origin_country": "JP",
  "original_language": "jp",
  "original_title": "MIAA-097 I found a teacher on the AV on the net, so I asked him to teach me how to have sex Nanaho Kase",
  "overview": "I searched for erotic videos on my smartphone and found an AV with a longing homeroom teacher! When I asked him to teach me how to have sex, I really agreed! !! Nanaho-sensei, a beautiful girl with big tits, can teach me not only classes but also naughty things ...! After-school premature ejaculation overcoming blowjob, cunnilingus practice during lunch break, practical training with just two people at home visit! The more you improve, the closer you are to the teacher. \"It's a secret only for two people?\" The way of SEX and the taste of love taught by the teacher I admired! [MOODYZ Campaign 30% OFF 3rd] has ended. * Click here for details such as privilege information",
  "popularity": 0,
  "poster_path": "https://fourhoi.com/miaa-097-uncensored-leak/cover.jpg",
  "production_companies": [
    {
      "id": "Moody's",
      "logo_path": "https://placehold.co/200",
      "name": "Moody's",
      "origin_country": "JP"
    }
  ],
  "production_countries": [
    {
      "iso_3166_1": "JP",
      "name": "Japan"
    }
  ],
  "release_date": "2019-06-08\n                            5 years ago\n                        \n                            6 years ago\n                        \n                            6 years ago\n                        \n                            6 years ago\n                        \n                            6 years ago\n                        ",
  "revenue": 0,
  "runtime": 156,
  "spoken_languages": [
    {
      "iso_639_1": "ja",
      "name": "Japanese"
    }
  ],
  "status": "Released",
  "tagline": "Adult",
  "title": "MIAA 097 Uncensored Leak",
  "video": null,
  "vote_average": 0,
  "vote_count": 0,
  "sources": [],
  "keywords": {
    "keywords": [
      {
        "id": null,
        "name": null
      }
    ]
  },
  "credits": {
    "cast": [
      {
        "adult": true,
        "gender": 1,
        "id": "Nanaho Kase",
        "known_for_department": "Acting",
        "name": "Nanaho Kase",
        "popularity": null,
        "profile_path": "https://placehold.co/200",
        "cast_id": null,
        "character": null,
        "credit_id": null,
        "order": null
      }
    ],
    "crew": [
      {
        "adult": true,
        "gender": null,
        "id": "Moody%27s",
        "known_for_department": "Directing",
        "name": "Moody's",
        "popularity": null,
        "profile_path": "https://placehold.co/200",
        "credit_id": null,
        "department": "Directing",
        "job": "Director"
      }
    ]
  }
}