{
  "adult": true,
  "backdrop_path": null,
  "belongs_to_collection": null,
  "budget": 0,
  "genres": [
    {
      "id": 49,
      "name": "Slut"
    },
    {
      "id": 53,
      "name": "Big Breasts"
    },
    {
      "id": 44,
      "name": "Big Breast Fetish"
    },
    {
      "id": 35,
      "name": "Individual"
    },
    {
      "id": 46,
      "name": "Ride"
    },
    {
      "id": 0,
      "name": "Tit Job"
    },
    {
      "id": 39,
      "name": "Hd"
    },
    {
      "id": 55,
      "name": "Exclusive"
    }
  ],
  "homepage": "https://missav.ai",
  "id": "pppd-289",
  "imdb_id": "pppd-289",
  "origin_country": "JP",
  "original_language": "jp",
  "original_title": "PPPD-289 Naked busty housekeeper Mao Hamasaki - Hamazaki Mao",
  "overview": "The housekeeper who asked you suddenly became naked? !! It shakes your boobs and takes care of your surroundings. Cleaning, washing, shopping, of course ... If you get sick, they will be happy to take care of your sexual treatment. We always keep in mind the service with sincerity.",
  "popularity": 0,
  "poster_path": "https://fourhoi.com/pppd-289/cover.jpg",
  "production_companies": [
    {
      "id": "OPPAI",
      "logo_path": "https://placehold.co/200",
      "name": "OPPAI",
      "origin_country": "JP"
    }
  ],
  "production_countries": [
    {
      "iso_3166_1": "JP",
      "name": "Japan"
    }
  ],
  "release_date": "2014-05-17\n                            2 weeks ago\n                        \n                            2 weeks ago\n                        \n                            2 weeks ago\n                        \n                            2 weeks ago\n                        \n                            2 weeks ago\n                        \n                            2 weeks ago\n                        \n                            2 weeks ago\n                        \n                            2 weeks ago\n                        \n                            2 weeks ago\n                        \n                            2 weeks ago\n                        ",
  "revenue": 0,
  "runtime": 118,
  "spoken_languages": [
    {
      "iso_639_1": "ja",
      "name": "Japanese"
    }
  ],
  "status": "Released",
  "tagline": "Adult",
  "title": "PPPD 289",
  "video": null,
  "vote_average": 0,
  "vote_count": 0,
  "sources": [],
  "keywords": {
    "keywords": [
      {
        "id": null,
        "name": null
      }
    ]
  },
  "credits": {
    "cast": [
      {
        "adult": true,
        "gender": 1,
        "id": "Hamazaki Mao",
        "known_for_department": "Acting",
        "name": "Hamazaki Mao",
        "popularity": null,
        "profile_path": "https://placehold.co/200",
        "cast_id": null,
        "character": null,
        "credit_id": null,
        "order": null
      }
    ],
    "crew": [
      {
        "adult": true,
        "gender": null,
        "id": "OPPAI",
        "known_for_department": "Directing",
        "name": "OPPAI",
        "popularity": null,
        "profile_path": "https://placehold.co/200",
        "credit_id": null,
        "department": "Directing",
        "job": "Director"
      }
    ]
  }
}