{
  "adult": true,
  "backdrop_path": null,
  "belongs_to_collection": null,
  "budget": 0,
  "genres": [
    {
      "id": 23,
      "name": "Pretty Girl"
    },
    {
      "id": 63,
      "name": "Individual"
    },
    {
      "id": 12,
      "name": "Promiscuous"
    },
    {
      "id": 41,
      "name": "Squirting"
    },
    {
      "id": 98,
      "name": "Bukkake"
    },
    {
      "id": 13,
      "name": "Sweating"
    },
    {
      "id": 88,
      "name": "Slim Pixelated"
    },
    {
      "id": 94,
      "name": "Hd"
    }
  ],
  "homepage": "https://missav.ai",
  "id": "tppn-009",
  "imdb_id": "tppn-009",
  "origin_country": "JP",
  "original_language": "jp",
  "original_title": "TPPN-009 Reason collapses in pleasure. Riku Minato",
  "overview": "Riku Minato's new door is pried open with sex that is completely immersed in pleasure. Far from ending with just once or twice, she pierces her pussy with a more intense piston. While bending over her body, when she climaxed countless times, Riku Minato's reason completely collapsed and she became a prisoner of pleasure that can only think about sex.",
  "popularity": 0,
  "poster_path": "https://fourhoi.com/tppn-009/cover.jpg",
  "production_companies": [
    {
      "id": "TEPPAN",
      "logo_path": "https://placehold.co/200",
      "name": "TEPPAN",
      "origin_country": "JP"
    }
  ],
  "production_countries": [
    {
      "iso_3166_1": "JP",
      "name": "Japan"
    }
  ],
  "release_date": "2014-05-30\n                            2 years ago\n                        \n                            2 years ago\n                        \n                            2 years ago\n                        \n                            2 years ago\n                        \n                            2 years ago\n                        \n                            2 years ago\n                        \n                            2 years ago\n                        \n                            2 years ago\n                        \n                            2 years ago\n                        \n                            2 years ago\n                        ",
  "revenue": 0,
  "runtime": 119,
  "spoken_languages": [
    {
      "iso_639_1": "ja",
      "name": "Japanese"
    }
  ],
  "status": "Released",
  "tagline": "Adult",
  "title": "TPPN 009",
  "video": null,
  "vote_average": 0,
  "vote_count": 0,
  "sources": [],
  "keywords": {
    "keywords": [
      {
        "id": null,
        "name": null
      }
    ]
  },
  "credits": {
    "cast": [
      {
        "adult": true,
        "gender": 1,
        "id": "Riku Minato",
        "known_for_department": "Acting",
        "name": "Riku Minato",
        "popularity": null,
        "profile_path": "https://placehold.co/200",
        "cast_id": null,
        "character": null,
        "credit_id": null,
        "order": null
      }
    ],
    "crew": [
      {
        "adult": true,
        "gender": null,
        "id": "TEPPAN",
        "known_for_department": "Directing",
        "name": "TEPPAN",
        "popularity": null,
        "profile_path": "https://placehold.co/200",
        "credit_id": null,
        "department": "Directing",
        "job": "Director"
      }
    ]
  }
}