{
  "adult": true,
  "backdrop_path": null,
  "belongs_to_collection": null,
  "budget": 0,
  "genres": [
    {
      "id": 33,
      "name": "Female College Student"
    },
    {
      "id": 37,
      "name": "Oral Sex"
    },
    {
      "id": 3,
      "name": "Masturbation"
    },
    {
      "id": 34,
      "name": "Orgy"
    }
  ],
  "homepage": "https://missav.ai",
  "id": "luk-011",
  "imdb_id": "luk-011",
  "origin_country": "JP",
  "original_language": "jp",
  "original_title": "LUK-011 Compensated dating record with an active female college student",
  "overview": "Real compensated dating document by 3 female college students! Three women attending a famous women's college need money for different reasons, so they sell their young and beautiful bodies. Men threaten to know their identity and call them and taste the bodies of female college students as long as they want! Three college girls get dirty by men at will! !",
  "popularity": 0,
  "poster_path": "https://fourhoi.com/luk-011/cover.jpg",
  "production_companies": [
    {
      "id": "ハヤブサ",
      "logo_path": "https://placehold.co/200",
      "name": "%E3%83%8F%E3%83%A4%E3%83%96%E3%82%B5",
      "origin_country": "JP"
    }
  ],
  "production_countries": [
    {
      "iso_3166_1": "JP",
      "name": "Japan"
    }
  ],
  "release_date": "2014-05-23",
  "revenue": 0,
  "runtime": 238,
  "spoken_languages": [
    {
      "iso_639_1": "ja",
      "name": "Japanese"
    }
  ],
  "status": "Released",
  "tagline": "Adult",
  "title": "LUK 011",
  "video": null,
  "vote_average": 0,
  "vote_count": 0,
  "sources": [],
  "keywords": {
    "keywords": [
      {
        "id": null,
        "name": null
      }
    ]
  },
  "credits": {
    "cast": [],
    "crew": [
      {
        "adult": true,
        "gender": null,
        "id": "%E3%83%8F%E3%83%A4%E3%83%96%E3%82%B5",
        "known_for_department": "Directing",
        "name": "ハヤブサ",
        "popularity": null,
        "profile_path": "https://placehold.co/200",
        "credit_id": null,
        "department": "Directing",
        "job": "Director"
      }
    ]
  }
}