{
  "adult": true,
  "backdrop_path": null,
  "belongs_to_collection": null,
  "budget": 0,
  "genres": [
    {
      "id": 96,
      "name": "Sneak Shots"
    },
    {
      "id": 96,
      "name": "Ordinary Person"
    },
    {
      "id": 81,
      "name": "Masturbate"
    },
    {
      "id": 33,
      "name": "Toy"
    }
  ],
  "homepage": "https://missav.ai",
  "id": "tat-001",
  "imdb_id": "tat-001",
  "origin_country": "JP",
  "original_language": "jp",
  "original_title": "TAT-001 A certain apparel maker employee training facility leaked video Toilet masturbation 1",
  "overview": "Voyeur video leaked from the accommodation training facility. There were many records of the stress during the training, or the naked appearance that unfolded after finishing the basket in a private room. Carefully selected and edited girls from a huge number of shooting tapes! Mr. Y, who was in charge of de S boobs, also praised it! !!",
  "popularity": 0,
  "poster_path": "https://fourhoi.com/tat-001/cover.jpg",
  "production_companies": [
    {
      "id": "ブレーントラストカンパニー",
      "logo_path": "https://placehold.co/200",
      "name": "%E3%83%96%E3%83%AC%E3%83%BC%E3%83%B3%E3%83%88%E3%83%A9%E3%82%B9%E3%83%88%E3%82%AB%E3%83%B3%E3%83%91%E3%83%8B%E3%83%BC",
      "origin_country": "JP"
    }
  ],
  "production_countries": [
    {
      "iso_3166_1": "JP",
      "name": "Japan"
    }
  ],
  "release_date": "2014-05-28",
  "revenue": 0,
  "runtime": 45,
  "spoken_languages": [
    {
      "iso_639_1": "ja",
      "name": "Japanese"
    }
  ],
  "status": "Released",
  "tagline": "Adult",
  "title": "TAT 001",
  "video": null,
  "vote_average": 0,
  "vote_count": 0,
  "sources": [],
  "keywords": {
    "keywords": [
      {
        "id": null,
        "name": null
      }
    ]
  },
  "credits": {
    "cast": [],
    "crew": [
      {
        "adult": true,
        "gender": null,
        "id": "%E3%83%96%E3%83%AC%E3%83%BC%E3%83%B3%E3%83%88%E3%83%A9%E3%82%B9%E3%83%88%E3%82%AB%E3%83%B3%E3%83%91%E3%83%8B%E3%83%BC",
        "known_for_department": "Directing",
        "name": "ブレーントラストカンパニー",
        "popularity": null,
        "profile_path": "https://placehold.co/200",
        "credit_id": null,
        "department": "Directing",
        "job": "Director"
      }
    ]
  }
}