{
  "adult": true,
  "backdrop_path": null,
  "belongs_to_collection": null,
  "budget": 0,
  "genres": [
    {
      "id": 16,
      "name": "Ol"
    },
    {
      "id": 37,
      "name": "Promiscuous"
    },
    {
      "id": 78,
      "name": "Creampie"
    },
    {
      "id": 68,
      "name": "Orgy"
    },
    {
      "id": 5,
      "name": "Collection"
    },
    {
      "id": 56,
      "name": "4 Hours Or More"
    },
    {
      "id": 64,
      "name": "Exclusive"
    }
  ],
  "homepage": "https://missav.ai",
  "id": "rezd-135",
  "imdb_id": "rezd-135",
  "origin_country": "JP",
  "original_language": "jp",
  "original_title": "REZD-135 Posts from people involved in M life insurance Learn from top sales! New Life Insurance Lady's Secret Training All Highlights \"A Woman's Body Is The Biggest Weapon To Win A Contract\"",
  "overview": "I'll show you everything! Life insurance lady with income disparity \"I just want to earn!\" \"Expert training\" for greedy newcomers only Top sales will teach you the secrets of how to get a contract! What is the sex technique of practical training assuming the branch manager as a customer? !",
  "popularity": 0,
  "poster_path": "https://fourhoi.com/rezd-135/cover.jpg",
  "production_companies": [
    {
      "id": "レッド",
      "logo_path": "https://placehold.co/200",
      "name": "%E3%83%AC%E3%83%83%E3%83%89",
      "origin_country": "JP"
    }
  ],
  "production_countries": [
    {
      "iso_3166_1": "JP",
      "name": "Japan"
    }
  ],
  "release_date": "2014-05-22",
  "revenue": 0,
  "runtime": 479,
  "spoken_languages": [
    {
      "iso_639_1": "ja",
      "name": "Japanese"
    }
  ],
  "status": "Released",
  "tagline": "Adult",
  "title": "REZD 135",
  "video": null,
  "vote_average": 0,
  "vote_count": 0,
  "sources": [],
  "keywords": {
    "keywords": [
      {
        "id": null,
        "name": null
      }
    ]
  },
  "credits": {
    "cast": [],
    "crew": [
      {
        "adult": true,
        "gender": null,
        "id": "%E3%83%AC%E3%83%83%E3%83%89",
        "known_for_department": "Directing",
        "name": "レッド",
        "popularity": null,
        "profile_path": "https://placehold.co/200",
        "credit_id": null,
        "department": "Directing",
        "job": "Director"
      }
    ]
  }
}