{
  "adult": true,
  "backdrop_path": null,
  "belongs_to_collection": null,
  "budget": 0,
  "genres": [
    {
      "id": 70,
      "name": "Uncensored leak"
    },
    {
      "id": 28,
      "name": "Uniform"
    },
    {
      "id": 74,
      "name": "High School Girl"
    },
    {
      "id": 8,
      "name": "Individual"
    },
    {
      "id": 16,
      "name": "Creampie"
    },
    {
      "id": 60,
      "name": "Masturbate"
    },
    {
      "id": 74,
      "name": "Selfie"
    },
    {
      "id": 25,
      "name": "Exclusive"
    },
    {
      "id": 34,
      "name": "Delusion"
    }
  ],
  "homepage": "https://missav.ai",
  "id": "jrba-015-uncensored-leak",
  "imdb_id": "jrba-015-uncensored-leak",
  "origin_country": "JP",
  "original_language": "jp",
  "original_title": "JRBA-015 Our favorite female student Ritsu-chan Nagasawa Ritsu - Ritsu Nagasawa",
  "overview": "An angel who goes on a uniform date with an old man even though she has a boyfriend. Anyway, I was able to do whatever I wanted to M-chan, who is weak against pressure, at a karaoke store and a love hotel.The sight of her having beautiful breasts and a loli body with freshly grown thin pussy hair that looks like an erotic anime is a must-see. We will secretly release a video of an innocent masochistic girl having a serious orgasm with her father! ! [*Please note that there may be some disturbance in the image or sound, but this is not a defect in the product itself.]",
  "popularity": 0,
  "poster_path": "https://fourhoi.com/jrba-015-uncensored-leak/cover.jpg",
  "production_companies": [
    {
      "id": "うさぎ/妄想族",
      "logo_path": "https://placehold.co/200",
      "name": "うさぎ/妄想族",
      "origin_country": "JP"
    }
  ],
  "production_countries": [
    {
      "iso_3166_1": "JP",
      "name": "Japan"
    }
  ],
  "release_date": "2023-12-09",
  "revenue": 0,
  "runtime": 191,
  "spoken_languages": [
    {
      "iso_639_1": "ja",
      "name": "Japanese"
    }
  ],
  "status": "Released",
  "tagline": "Adult",
  "title": "JRBA 015 Uncensored Leak",
  "video": null,
  "vote_average": 0,
  "vote_count": 0,
  "sources": [],
  "keywords": {
    "keywords": [
      {
        "id": null,
        "name": null
      }
    ]
  },
  "credits": {
    "cast": [
      {
        "adult": true,
        "gender": 1,
        "id": "Ritsu Nagasawa",
        "known_for_department": "Acting",
        "name": "Ritsu Nagasawa",
        "popularity": null,
        "profile_path": "https://placehold.co/200",
        "cast_id": null,
        "character": null,
        "credit_id": null,
        "order": null
      }
    ],
    "crew": [
      {
        "adult": true,
        "gender": null,
        "id": "%E5%A6%84%E6%83%B3%E6%97%8F",
        "known_for_department": "Directing",
        "name": "うさぎ/妄想族",
        "popularity": null,
        "profile_path": "https://placehold.co/200",
        "credit_id": null,
        "department": "Directing",
        "job": "Director"
      }
    ]
  }
}