{
  "adult": true,
  "backdrop_path": null,
  "belongs_to_collection": null,
  "budget": 0,
  "genres": [
    {
      "id": 71,
      "name": "Restraint"
    },
    {
      "id": 51,
      "name": "Big Breasts"
    },
    {
      "id": 9,
      "name": "Individual"
    },
    {
      "id": 98,
      "name": "Promiscuous"
    },
    {
      "id": 85,
      "name": "Hot Spring"
    },
    {
      "id": 45,
      "name": "Creampie"
    },
    {
      "id": 87,
      "name": "Tit Job"
    },
    {
      "id": 12,
      "name": "Bitch"
    },
    {
      "id": 67,
      "name": "Hd"
    }
  ],
  "homepage": "https://missav.ai",
  "id": "bank-013",
  "imdb_id": "bank-013",
  "origin_country": "JP",
  "original_language": "jp",
  "original_title": "BANK-013 Creampie open-air hot spring rocket boobs I cup but slender! Nipple Bing & De M Nasty Woman Hikari Sena",
  "overview": "I cup big breasts with the best shape and elasticity that do not hang down at all! A bright and cute woman who keeps smiling is a bitch who loves super H! Because it is de M, when I blame 3 points for the first time in my life, I have convulsions. I enjoyed a wide range of things such as footjob and restraint play with rocket milk fucking and stockings! Don't miss the boobs that sway violently! [* The image and sound may be distorted, but please note that this is not a defect of the product itself.]",
  "popularity": 0,
  "poster_path": "https://fourhoi.com/bank-013/cover.jpg",
  "production_companies": [
    {
      "id": "ま○こ銀行",
      "logo_path": "https://placehold.co/200",
      "name": "ま○こ銀行",
      "origin_country": "JP"
    }
  ],
  "production_countries": [
    {
      "iso_3166_1": "JP",
      "name": "Japan"
    }
  ],
  "release_date": "2020-09-11",
  "revenue": 0,
  "runtime": 155,
  "spoken_languages": [
    {
      "iso_639_1": "ja",
      "name": "Japanese"
    }
  ],
  "status": "Released",
  "tagline": "Adult",
  "title": "BANK 013",
  "video": null,
  "vote_average": 0,
  "vote_count": 0,
  "sources": [],
  "keywords": {
    "keywords": [
      {
        "id": null,
        "name": null
      }
    ]
  },
  "credits": {
    "cast": [
      {
        "adult": true,
        "gender": 1,
        "id": "Hikari Sena",
        "known_for_department": "Acting",
        "name": "Hikari Sena",
        "popularity": null,
        "profile_path": "https://placehold.co/200",
        "cast_id": null,
        "character": null,
        "credit_id": null,
        "order": null
      }
    ],
    "crew": [
      {
        "adult": true,
        "gender": null,
        "id": "%E3%81%BE%E2%97%8B%E3%81%93%E9%8A%80%E8%A1%8C",
        "known_for_department": "Directing",
        "name": "ま○こ銀行",
        "popularity": null,
        "profile_path": "https://placehold.co/200",
        "credit_id": null,
        "department": "Directing",
        "job": "Director"
      }
    ]
  }
}