{
  "adult": true,
  "backdrop_path": null,
  "belongs_to_collection": null,
  "budget": 0,
  "genres": [
    {
      "id": 2,
      "name": "Pretty Girl"
    },
    {
      "id": 36,
      "name": "Individual"
    },
    {
      "id": 84,
      "name": "Fantasy"
    },
    {
      "id": 77,
      "name": "Elder Sister"
    },
    {
      "id": 75,
      "name": "Creampie"
    },
    {
      "id": 49,
      "name": "Masturbate"
    },
    {
      "id": 28,
      "name": "Subjective Perspective"
    },
    {
      "id": 93,
      "name": "Hd"
    }
  ],
  "homepage": "https://missav.ai",
  "id": "etqr-157",
  "imdb_id": "etqr-157",
  "origin_country": "JP",
  "original_language": "jp",
  "original_title": "ETQR-157 [Delusional subjectivity] A ferocious courtship of a younger sister who is too yandere! Ichika Matsumoto",
  "overview": "My sister can't be so lewd! !! Ichika, my younger sister who loves me, suddenly turns into a naughty girl on the day of ovulation! Delusional masturbation while taking out my pants and sniffing! !! I was courted by my sister who couldn't control her estrus and finally had sex with her! Begging for my semen with a pregnancy begging dirty word while being alive many times! [* The image and sound may be distorted, but please note that this is not a defect of the product itself.]",
  "popularity": 0,
  "poster_path": "https://fourhoi.com/etqr-157/cover.jpg",
  "production_companies": [
    {
      "id": "エロタイム",
      "logo_path": "https://placehold.co/200",
      "name": "%E3%82%A8%E3%83%AD%E3%82%BF%E3%82%A4%E3%83%A0",
      "origin_country": "JP"
    }
  ],
  "production_countries": [
    {
      "iso_3166_1": "JP",
      "name": "Japan"
    }
  ],
  "release_date": "2020-09-04\n                            4 days ago\n                        \n                            1 week ago\n                        \n                            1 week ago\n                        \n                            2 weeks ago\n                        \n                            2 weeks ago\n                        \n                            2 weeks ago\n                        \n                            2 weeks ago\n                        \n                            2 weeks ago\n                        \n                            2 weeks ago\n                        \n                            2 weeks ago\n                        ",
  "revenue": 0,
  "runtime": 67,
  "spoken_languages": [
    {
      "iso_639_1": "ja",
      "name": "Japanese"
    }
  ],
  "status": "Released",
  "tagline": "Adult",
  "title": "ETQR 157",
  "video": null,
  "vote_average": 0,
  "vote_count": 0,
  "sources": [],
  "keywords": {
    "keywords": [
      {
        "id": null,
        "name": null
      }
    ]
  },
  "credits": {
    "cast": [
      {
        "adult": true,
        "gender": 1,
        "id": "Ichika Matsumoto",
        "known_for_department": "Acting",
        "name": "Ichika Matsumoto",
        "popularity": null,
        "profile_path": "https://placehold.co/200",
        "cast_id": null,
        "character": null,
        "credit_id": null,
        "order": null
      }
    ],
    "crew": [
      {
        "adult": true,
        "gender": null,
        "id": "%E3%82%A8%E3%83%AD%E3%82%BF%E3%82%A4%E3%83%A0",
        "known_for_department": "Directing",
        "name": "エロタイム",
        "popularity": null,
        "profile_path": "https://placehold.co/200",
        "credit_id": null,
        "department": "Directing",
        "job": "Director"
      }
    ]
  }
}