{
  "adult": true,
  "backdrop_path": null,
  "belongs_to_collection": null,
  "budget": 0,
  "genres": [
    {
      "id": 88,
      "name": "Mature Woman"
    },
    {
      "id": 47,
      "name": "Wife"
    },
    {
      "id": 7,
      "name": "Hit On Girls"
    },
    {
      "id": 9,
      "name": "Hd"
    },
    {
      "id": 91,
      "name": "Exclusive"
    },
    {
      "id": 3,
      "name": "Beautiful Breasts"
    }
  ],
  "homepage": "https://missav.ai",
  "id": "avkh-176",
  "imdb_id": "avkh-176",
  "origin_country": "JP",
  "original_language": "jp",
  "original_title": "AVKH-176 Reona Kirishima",
  "overview": "",
  "popularity": 0,
  "poster_path": "https://fourhoi.com/avkh-176/cover.jpg",
  "production_companies": [
    {
      "id": "恋する花嫁",
      "logo_path": "https://placehold.co/200",
      "name": "恋する花嫁",
      "origin_country": "JP"
    }
  ],
  "production_countries": [
    {
      "iso_3166_1": "JP",
      "name": "Japan"
    }
  ],
  "release_date": "2020-09-03",
  "revenue": 0,
  "runtime": 81,
  "spoken_languages": [
    {
      "iso_639_1": "ja",
      "name": "Japanese"
    }
  ],
  "status": "Released",
  "tagline": "Adult",
  "title": "AVKH 176",
  "video": null,
  "vote_average": 0,
  "vote_count": 0,
  "sources": [],
  "keywords": {
    "keywords": [
      {
        "id": null,
        "name": null
      }
    ]
  },
  "credits": {
    "cast": [],
    "crew": [
      {
        "adult": true,
        "gender": null,
        "id": "%E6%81%8B%E3%81%99%E3%82%8B%E8%8A%B1%E5%AB%81",
        "known_for_department": "Directing",
        "name": "恋する花嫁",
        "popularity": null,
        "profile_path": "https://placehold.co/200",
        "credit_id": null,
        "department": "Directing",
        "job": "Director"
      }
    ]
  }
}