{
  "adult": true,
  "backdrop_path": null,
  "belongs_to_collection": null,
  "budget": 0,
  "genres": [
    {
      "id": 14,
      "name": "Slut"
    },
    {
      "id": 79,
      "name": "Wife"
    },
    {
      "id": 42,
      "name": "Elder Sister"
    },
    {
      "id": 95,
      "name": "Creampie"
    },
    {
      "id": 10,
      "name": "Tit Job"
    },
    {
      "id": 93,
      "name": "Hd"
    }
  ],
  "homepage": "https://missav.ai",
  "id": "vandr-112",
  "imdb_id": "vandr-112",
  "origin_country": "JP",
  "original_language": "jp",
  "original_title": "VANDR-112 Even though I have a lot of playren, my sister is undergoing fertility treatment and cannot have playren at all. Such an older sister gathers married women who are fertility treatment friends and forces me to make sex every day - Kudo Misa",
  "overview": "\"Give me a lively sperm\" Housewives suffering from infertility flock to a man. My sister who asks her younger brother to have sex with herself, and her sister's request escalate, and she is forced to bring her friend's fertility treatment companion on a daily basis and do vaginal cum shot SEX. Fucking, face sitting, triple blowjob, vaginal cum shot and actually a dreamlike situation with 1 man vs 5 women!",
  "popularity": 0,
  "poster_path": "https://fourhoi.com/vandr-112/cover.jpg",
  "production_companies": [
    {
      "id": "V＆R PRODUCE",
      "logo_path": "https://placehold.co/200",
      "name": "V%EF%BC%86R%20PRODUCE",
      "origin_country": "JP"
    }
  ],
  "production_countries": [
    {
      "iso_3166_1": "JP",
      "name": "Japan"
    }
  ],
  "release_date": "2014-05-10",
  "revenue": 0,
  "runtime": 224,
  "spoken_languages": [
    {
      "iso_639_1": "ja",
      "name": "Japanese"
    }
  ],
  "status": "Released",
  "tagline": "Adult",
  "title": "VANDR 112",
  "video": null,
  "vote_average": 0,
  "vote_count": 0,
  "sources": [],
  "keywords": {
    "keywords": [
      {
        "id": null,
        "name": null
      }
    ]
  },
  "credits": {
    "cast": [
      {
        "adult": true,
        "gender": 1,
        "id": "Kudo Misa",
        "known_for_department": "Acting",
        "name": "Kudo Misa",
        "popularity": null,
        "profile_path": "https://placehold.co/200",
        "cast_id": null,
        "character": null,
        "credit_id": null,
        "order": null
      },
      {
        "adult": true,
        "gender": 1,
        "id": "Mizuki Yume",
        "known_for_department": "Acting",
        "name": "Mizuki Yume",
        "popularity": null,
        "profile_path": "https://placehold.co/200",
        "cast_id": null,
        "character": null,
        "credit_id": null,
        "order": null
      },
      {
        "adult": true,
        "gender": 1,
        "id": "Aiko Endo",
        "known_for_department": "Acting",
        "name": "Aiko Endo",
        "popularity": null,
        "profile_path": "https://placehold.co/200",
        "cast_id": null,
        "character": null,
        "credit_id": null,
        "order": null
      },
      {
        "adult": true,
        "gender": 1,
        "id": "Miu Watanabe",
        "known_for_department": "Acting",
        "name": "Miu Watanabe",
        "popularity": null,
        "profile_path": "https://placehold.co/200",
        "cast_id": null,
        "character": null,
        "credit_id": null,
        "order": null
      },
      {
        "adult": true,
        "gender": 1,
        "id": "Misakura Yoshida",
        "known_for_department": "Acting",
        "name": "Misakura Yoshida",
        "popularity": null,
        "profile_path": "https://placehold.co/200",
        "cast_id": null,
        "character": null,
        "credit_id": null,
        "order": null
      }
    ],
    "crew": [
      {
        "adult": true,
        "gender": null,
        "id": "V%EF%BC%86R%20PRODUCE",
        "known_for_department": "Directing",
        "name": "V＆R PRODUCE",
        "popularity": null,
        "profile_path": "https://placehold.co/200",
        "credit_id": null,
        "department": "Directing",
        "job": "Director"
      }
    ]
  }
}