{
  "adult": true,
  "backdrop_path": null,
  "belongs_to_collection": null,
  "budget": 0,
  "genres": [
    {
      "id": 99,
      "name": "Uncensored leak"
    },
    {
      "id": 66,
      "name": "Lesbian"
    },
    {
      "id": 29,
      "name": "Ordinary Person"
    },
    {
      "id": 64,
      "name": "Creampie"
    },
    {
      "id": 73,
      "name": "Orgy"
    },
    {
      "id": 30,
      "name": "Big Pennis"
    },
    {
      "id": 75,
      "name": "Hd"
    },
    {
      "id": 94,
      "name": "Exclusive"
    },
    {
      "id": 42,
      "name": "Delusion"
    },
    {
      "id": 57,
      "name": "4K"
    }
  ],
  "homepage": "https://missav.ai",
  "id": "halt-038-uncensored-leak",
  "imdb_id": "halt-038-uncensored-leak",
  "origin_country": "JP",
  "original_language": "jp",
  "original_title": "HALT-038 [Miwa & Yuzuna] Two short JDs. Even though she looks quiet...the sexy gap is the best lol First 3P. Did you unconsciously come back to your senses as you cum from the pleasure of the big cock? ? Pregnancy Regret SEX",
  "overview": "It's the best! ! I am grateful for this world where I can easily meet people. . Those who like amateurs will understand. Two short JDs. You look quiet, yes, you have short hair. The gap is crazy! ! I didn't miss Miwa-chan's hard work! ! Natural harem 3P creampie. Just follow your sexual desires...this is fine...",
  "popularity": 0,
  "poster_path": "https://fourhoi.com/halt-038-uncensored-leak/cover.jpg",
  "production_companies": [
    {
      "id": "HALENTINO/妄想族",
      "logo_path": "https://placehold.co/200",
      "name": "HALENTINO/妄想族",
      "origin_country": "JP"
    }
  ],
  "production_countries": [
    {
      "iso_3166_1": "JP",
      "name": "Japan"
    }
  ],
  "release_date": "2023-12-16",
  "revenue": 0,
  "runtime": 136,
  "spoken_languages": [
    {
      "iso_639_1": "ja",
      "name": "Japanese"
    }
  ],
  "status": "Released",
  "tagline": "Adult",
  "title": "HALT 038 Uncensored Leak",
  "video": null,
  "vote_average": 0,
  "vote_count": 0,
  "sources": [],
  "keywords": {
    "keywords": [
      {
        "id": null,
        "name": null
      }
    ]
  },
  "credits": {
    "cast": [],
    "crew": [
      {
        "adult": true,
        "gender": null,
        "id": "%E5%A6%84%E6%83%B3%E6%97%8F",
        "known_for_department": "Directing",
        "name": "HALENTINO/妄想族",
        "popularity": null,
        "profile_path": "https://placehold.co/200",
        "credit_id": null,
        "department": "Directing",
        "job": "Director"
      }
    ]
  }
}